README.md
setup.py
stackdriver_formatter/__init__.py
stackdriver_formatter/exceptions.py
stackdriver_formatter/formatters.py
stackdriver_formatter/logging.py
stackdriver_formatter.egg-info/PKG-INFO
stackdriver_formatter.egg-info/SOURCES.txt
stackdriver_formatter.egg-info/dependency_links.txt
stackdriver_formatter.egg-info/requires.txt
stackdriver_formatter.egg-info/top_level.txt
tests/unit/__init__.py
tests/unit/stackdriver_formatter/__init__.py
tests/unit/stackdriver_formatter/test_logging.py