Metadata-Version: 1.0
Name: stackdriver-formatter
Version: 1.0.2
Summary: Stackdriver Formatter
Home-page: https://github.com/stone-payments/stackdriver-formatter
Author: UNKNOWN
Author-email: UNKNOWN
License: UNKNOWN
Platform: UNKNOWN
